newsdejavu/__init__.py
newsdejavu/ner_mask_embed_query.py
newsdejavu/download/__init__.py
newsdejavu/download/american_stories.py
newsdejavu/download/download.py
newsdejavu/embed/__init__.py
newsdejavu/embed/embed.py
newsdejavu/ner/__init__.py
newsdejavu/ner/ner.py
newsdejavu/query/__init__.py
newsdejavu/query/query.py
newsdejavu/utils/__init__.py
newsdejavu/utils/clean_text.py
newsdejavu/utils/dataset.py
newsdejavu/utils/wrangling.py
newsdejavu-0.0.3.dist-info/LICENSE
newsdejavu-0.0.3.dist-info/METADATA
newsdejavu-0.0.3.dist-info/WHEEL
newsdejavu-0.0.3.dist-info/top_level.txt
newsdejavu-0.0.3.dist-info/RECORD
